[
  {
    "YTDCount": 5,
    "Year": 2019,
    "Offense": "Arson"
  },
  {
    "YTDCount": 7,
    "Year": 2020,
    "Offense": "Arson",
    "PrevYTDCount": 5,
    "YTDPercentageChange": 40
  },
  {
    "YTDCount": 9,
    "Year": 2021,
    "Offense": "Arson",
    "PrevYTDCount": 7,
    "YTDPercentageChange": 28.5714
  },
  {
    "YTDCount": 8,
    "Year": 2022,
    "Offense": "Arson",
    "PrevYTDCount": 9,
    "YTDPercentageChange": -11.1111
  },
  {
    "YTDCount": 14,
    "Year": 2023,
    "Offense": "Arson",
    "PrevYTDCount": 8,
    "YTDPercentageChange": 75
  },
  {
    "YTDCount": 7,
    "Year": 2024,
    "Offense": "Arson",
    "PrevYTDCount": 14,
    "YTDPercentageChange": -50
  },
  {
    "YTDCount": 5,
    "Year": 2025,
    "Offense": "Arson",
    "PrevYTDCount": 7,
    "YTDPercentageChange": -28.5714
  }
]
