[
  {
    "YTDCount": 34,
    "Year": 2019,
    "Offense": "Arson"
  },
  {
    "YTDCount": 51,
    "Year": 2020,
    "Offense": "Arson",
    "PrevYTDCount": 34,
    "YTDPercentageChange": 50
  },
  {
    "YTDCount": 47,
    "Year": 2021,
    "Offense": "Arson",
    "PrevYTDCount": 51,
    "YTDPercentageChange": -7.8431
  },
  {
    "YTDCount": 47,
    "Year": 2022,
    "Offense": "Arson",
    "PrevYTDCount": 47,
    "YTDPercentageChange": 0
  },
  {
    "YTDCount": 64,
    "Year": 2023,
    "Offense": "Arson",
    "PrevYTDCount": 47,
    "YTDPercentageChange": 36.1702
  },
  {
    "YTDCount": 59,
    "Year": 2024,
    "Offense": "Arson",
    "PrevYTDCount": 64,
    "YTDPercentageChange": -7.8125
  },
  {
    "YTDCount": 42,
    "Year": 2025,
    "Offense": "Arson",
    "PrevYTDCount": 59,
    "YTDPercentageChange": -28.8136
  }
]
