[
  {
    "YTDCount": 2161,
    "Year": 2019,
    "Offense": "Aggravated Assault"
  },
  {
    "YTDCount": 2760,
    "Year": 2020,
    "Offense": "Aggravated Assault",
    "PrevYTDCount": 2161,
    "YTDPercentageChange": 27.7186
  },
  {
    "YTDCount": 2915,
    "Year": 2021,
    "Offense": "Aggravated Assault",
    "PrevYTDCount": 2760,
    "YTDPercentageChange": 5.6159
  },
  {
    "YTDCount": 2959,
    "Year": 2022,
    "Offense": "Aggravated Assault",
    "PrevYTDCount": 2915,
    "YTDPercentageChange": 1.5094
  },
  {
    "YTDCount": 2791,
    "Year": 2023,
    "Offense": "Aggravated Assault",
    "PrevYTDCount": 2959,
    "YTDPercentageChange": -5.6776
  },
  {
    "YTDCount": 2823,
    "Year": 2024,
    "Offense": "Aggravated Assault",
    "PrevYTDCount": 2791,
    "YTDPercentageChange": 1.1465
  },
  {
    "YTDCount": 2663,
    "Year": 2025,
    "Offense": "Aggravated Assault",
    "PrevYTDCount": 2823,
    "YTDPercentageChange": -5.6677
  }
]
