[
  {
    "YTDCount": 318,
    "Year": 2019,
    "Offense": "Aggravated Assault"
  },
  {
    "YTDCount": 351,
    "Year": 2020,
    "Offense": "Aggravated Assault",
    "PrevYTDCount": 318,
    "YTDPercentageChange": 10.3774
  },
  {
    "YTDCount": 306,
    "Year": 2021,
    "Offense": "Aggravated Assault",
    "PrevYTDCount": 351,
    "YTDPercentageChange": -12.8205
  },
  {
    "YTDCount": 450,
    "Year": 2022,
    "Offense": "Aggravated Assault",
    "PrevYTDCount": 306,
    "YTDPercentageChange": 47.0588
  },
  {
    "YTDCount": 384,
    "Year": 2023,
    "Offense": "Aggravated Assault",
    "PrevYTDCount": 450,
    "YTDPercentageChange": -14.6667
  },
  {
    "YTDCount": 420,
    "Year": 2024,
    "Offense": "Aggravated Assault",
    "PrevYTDCount": 384,
    "YTDPercentageChange": 9.375
  },
  {
    "YTDCount": 369,
    "Year": 2025,
    "Offense": "Aggravated Assault",
    "PrevYTDCount": 420,
    "YTDPercentageChange": -12.1429
  }
]
