[
  {
    "YTDCount": 1450,
    "Year": 2019,
    "Offense": "Burglary/Breaking & Entering"
  },
  {
    "YTDCount": 1882,
    "Year": 2020,
    "Offense": "Burglary/Breaking & Entering",
    "PrevYTDCount": 1450,
    "YTDPercentageChange": 29.7931
  },
  {
    "YTDCount": 1220,
    "Year": 2021,
    "Offense": "Burglary/Breaking & Entering",
    "PrevYTDCount": 1882,
    "YTDPercentageChange": -35.1753
  },
  {
    "YTDCount": 1286,
    "Year": 2022,
    "Offense": "Burglary/Breaking & Entering",
    "PrevYTDCount": 1220,
    "YTDPercentageChange": 5.4098
  },
  {
    "YTDCount": 1170,
    "Year": 2023,
    "Offense": "Burglary/Breaking & Entering",
    "PrevYTDCount": 1286,
    "YTDPercentageChange": -9.0202
  },
  {
    "YTDCount": 1164,
    "Year": 2024,
    "Offense": "Burglary/Breaking & Entering",
    "PrevYTDCount": 1170,
    "YTDPercentageChange": -0.5128
  },
  {
    "YTDCount": 994,
    "Year": 2025,
    "Offense": "Burglary/Breaking & Entering",
    "PrevYTDCount": 1164,
    "YTDPercentageChange": -14.6048
  }
]
