[
  {
    "YTDCount": 2126,
    "Year": 2019,
    "Offense": "Burglary/Breaking & Entering"
  },
  {
    "YTDCount": 2720,
    "Year": 2020,
    "Offense": "Burglary/Breaking & Entering",
    "PrevYTDCount": 2126,
    "YTDPercentageChange": 27.9398
  },
  {
    "YTDCount": 1684,
    "Year": 2021,
    "Offense": "Burglary/Breaking & Entering",
    "PrevYTDCount": 2720,
    "YTDPercentageChange": -38.0882
  },
  {
    "YTDCount": 1894,
    "Year": 2022,
    "Offense": "Burglary/Breaking & Entering",
    "PrevYTDCount": 1684,
    "YTDPercentageChange": 12.4703
  },
  {
    "YTDCount": 1870,
    "Year": 2023,
    "Offense": "Burglary/Breaking & Entering",
    "PrevYTDCount": 1894,
    "YTDPercentageChange": -1.2672
  },
  {
    "YTDCount": 1714,
    "Year": 2024,
    "Offense": "Burglary/Breaking & Entering",
    "PrevYTDCount": 1870,
    "YTDPercentageChange": -8.3422
  }
]
