[
  {
    "YTDCount": 1476,
    "Year": 2019,
    "Offense": "Burglary/Breaking & Entering"
  },
  {
    "YTDCount": 1938,
    "Year": 2020,
    "Offense": "Burglary/Breaking & Entering",
    "PrevYTDCount": 1476,
    "YTDPercentageChange": 31.3008
  },
  {
    "YTDCount": 1250,
    "Year": 2021,
    "Offense": "Burglary/Breaking & Entering",
    "PrevYTDCount": 1938,
    "YTDPercentageChange": -35.5005
  },
  {
    "YTDCount": 1316,
    "Year": 2022,
    "Offense": "Burglary/Breaking & Entering",
    "PrevYTDCount": 1250,
    "YTDPercentageChange": 5.28
  },
  {
    "YTDCount": 1206,
    "Year": 2023,
    "Offense": "Burglary/Breaking & Entering",
    "PrevYTDCount": 1316,
    "YTDPercentageChange": -8.3587
  },
  {
    "YTDCount": 1166,
    "Year": 2024,
    "Offense": "Burglary/Breaking & Entering",
    "PrevYTDCount": 1206,
    "YTDPercentageChange": -3.3167
  }
]
