[
  {
    "YTDCount": 0,
    "Year": 2019,
    "Offense": "Carjacking - Subset of Robbery"
  },
  {
    "YTDCount": 11,
    "Year": 2020,
    "Offense": "Carjacking - Subset of Robbery"
  },
  {
    "YTDCount": 301,
    "Year": 2021,
    "Offense": "Carjacking - Subset of Robbery",
    "PrevYTDCount": 11,
    "YTDPercentageChange": 2636.3636
  },
  {
    "YTDCount": 380,
    "Year": 2022,
    "Offense": "Carjacking - Subset of Robbery",
    "PrevYTDCount": 301,
    "YTDPercentageChange": 26.2458
  },
  {
    "YTDCount": 184,
    "Year": 2023,
    "Offense": "Carjacking - Subset of Robbery",
    "PrevYTDCount": 380,
    "YTDPercentageChange": -51.5789
  },
  {
    "YTDCount": 185,
    "Year": 2024,
    "Offense": "Carjacking - Subset of Robbery",
    "PrevYTDCount": 184,
    "YTDPercentageChange": 0.5435
  },
  {
    "YTDCount": 121,
    "Year": 2025,
    "Offense": "Carjacking - Subset of Robbery",
    "PrevYTDCount": 185,
    "YTDPercentageChange": -34.5946
  }
]
