[
  {
    "YTDCount": 0,
    "Year": 2019,
    "Offense": "Carjacking - Subset of Robbery"
  },
  {
    "YTDCount": 1,
    "Year": 2020,
    "Offense": "Carjacking - Subset of Robbery"
  },
  {
    "YTDCount": 61,
    "Year": 2021,
    "Offense": "Carjacking - Subset of Robbery",
    "PrevYTDCount": 1,
    "YTDPercentageChange": 6000
  },
  {
    "YTDCount": 84,
    "Year": 2022,
    "Offense": "Carjacking - Subset of Robbery",
    "PrevYTDCount": 61,
    "YTDPercentageChange": 37.7049
  },
  {
    "YTDCount": 46,
    "Year": 2023,
    "Offense": "Carjacking - Subset of Robbery",
    "PrevYTDCount": 84,
    "YTDPercentageChange": -45.2381
  },
  {
    "YTDCount": 37,
    "Year": 2024,
    "Offense": "Carjacking - Subset of Robbery",
    "PrevYTDCount": 46,
    "YTDPercentageChange": -19.5652
  },
  {
    "YTDCount": 24,
    "Year": 2025,
    "Offense": "Carjacking - Subset of Robbery",
    "PrevYTDCount": 37,
    "YTDPercentageChange": -35.1351
  }
]
