[
  {
    "YTDCount": 665,
    "Year": 2019,
    "Offense": "Domestic Aggravated Assault - Subset of Assault"
  },
  {
    "YTDCount": 614,
    "Year": 2020,
    "Offense": "Domestic Aggravated Assault - Subset of Assault",
    "PrevYTDCount": 665,
    "YTDPercentageChange": -7.6692
  },
  {
    "YTDCount": 536,
    "Year": 2021,
    "Offense": "Domestic Aggravated Assault - Subset of Assault",
    "PrevYTDCount": 614,
    "YTDPercentageChange": -12.7036
  },
  {
    "YTDCount": 679,
    "Year": 2022,
    "Offense": "Domestic Aggravated Assault - Subset of Assault",
    "PrevYTDCount": 536,
    "YTDPercentageChange": 26.6791
  },
  {
    "YTDCount": 661,
    "Year": 2023,
    "Offense": "Domestic Aggravated Assault - Subset of Assault",
    "PrevYTDCount": 679,
    "YTDPercentageChange": -2.651
  },
  {
    "YTDCount": 665,
    "Year": 2024,
    "Offense": "Domestic Aggravated Assault - Subset of Assault",
    "PrevYTDCount": 661,
    "YTDPercentageChange": 0.6051
  }
]
