[
  {
    "YTDCount": 637,
    "Year": 2019,
    "Offense": "Domestic Aggravated Assault - Subset of Assault"
  },
  {
    "YTDCount": 589,
    "Year": 2020,
    "Offense": "Domestic Aggravated Assault - Subset of Assault",
    "PrevYTDCount": 637,
    "YTDPercentageChange": -7.5353
  },
  {
    "YTDCount": 515,
    "Year": 2021,
    "Offense": "Domestic Aggravated Assault - Subset of Assault",
    "PrevYTDCount": 589,
    "YTDPercentageChange": -12.5637
  },
  {
    "YTDCount": 645,
    "Year": 2022,
    "Offense": "Domestic Aggravated Assault - Subset of Assault",
    "PrevYTDCount": 515,
    "YTDPercentageChange": 25.2427
  },
  {
    "YTDCount": 632,
    "Year": 2023,
    "Offense": "Domestic Aggravated Assault - Subset of Assault",
    "PrevYTDCount": 645,
    "YTDPercentageChange": -2.0155
  },
  {
    "YTDCount": 641,
    "Year": 2024,
    "Offense": "Domestic Aggravated Assault - Subset of Assault",
    "PrevYTDCount": 632,
    "YTDPercentageChange": 1.4241
  }
]
