[
  {
    "YTDCount": 951,
    "Year": 2019,
    "Offense": "All Other Larceny"
  },
  {
    "YTDCount": 1085,
    "Year": 2020,
    "Offense": "All Other Larceny",
    "PrevYTDCount": 951,
    "YTDPercentageChange": 14.0904
  },
  {
    "YTDCount": 799,
    "Year": 2021,
    "Offense": "All Other Larceny",
    "PrevYTDCount": 1085,
    "YTDPercentageChange": -26.3594
  },
  {
    "YTDCount": 958,
    "Year": 2022,
    "Offense": "All Other Larceny",
    "PrevYTDCount": 799,
    "YTDPercentageChange": 19.8999
  },
  {
    "YTDCount": 886,
    "Year": 2023,
    "Offense": "All Other Larceny",
    "PrevYTDCount": 958,
    "YTDPercentageChange": -7.5157
  },
  {
    "YTDCount": 1131,
    "Year": 2024,
    "Offense": "All Other Larceny",
    "PrevYTDCount": 886,
    "YTDPercentageChange": 27.6524
  },
  {
    "YTDCount": 906,
    "Year": 2025,
    "Offense": "All Other Larceny",
    "PrevYTDCount": 1131,
    "YTDPercentageChange": -19.8939
  },
  {
    "YTDCount": 662,
    "Year": 2019,
    "Offense": "Theft From Motor Vehicle"
  },
  {
    "YTDCount": 771,
    "Year": 2020,
    "Offense": "Theft From Motor Vehicle",
    "PrevYTDCount": 662,
    "YTDPercentageChange": 16.4653
  },
  {
    "YTDCount": 502,
    "Year": 2021,
    "Offense": "Theft From Motor Vehicle",
    "PrevYTDCount": 771,
    "YTDPercentageChange": -34.8898
  },
  {
    "YTDCount": 604,
    "Year": 2022,
    "Offense": "Theft From Motor Vehicle",
    "PrevYTDCount": 502,
    "YTDPercentageChange": 20.3187
  },
  {
    "YTDCount": 600,
    "Year": 2023,
    "Offense": "Theft From Motor Vehicle",
    "PrevYTDCount": 604,
    "YTDPercentageChange": -0.6623
  },
  {
    "YTDCount": 589,
    "Year": 2024,
    "Offense": "Theft From Motor Vehicle",
    "PrevYTDCount": 600,
    "YTDPercentageChange": -1.8333
  },
  {
    "YTDCount": 702,
    "Year": 2025,
    "Offense": "Theft From Motor Vehicle",
    "PrevYTDCount": 589,
    "YTDPercentageChange": 19.1851
  },
  {
    "YTDCount": 2,
    "Year": 2019,
    "Offense": "Pocket-picking"
  },
  {
    "YTDCount": 2,
    "Year": 2020,
    "Offense": "Pocket-picking",
    "PrevYTDCount": 2,
    "YTDPercentageChange": 0
  },
  {
    "YTDCount": 0,
    "Year": 2021,
    "Offense": "Pocket-picking",
    "PrevYTDCount": 2,
    "YTDPercentageChange": -100
  },
  {
    "YTDCount": 0,
    "Year": 2022,
    "Offense": "Pocket-picking"
  },
  {
    "YTDCount": 0,
    "Year": 2023,
    "Offense": "Pocket-picking"
  },
  {
    "YTDCount": 0,
    "Year": 2024,
    "Offense": "Pocket-picking"
  },
  {
    "YTDCount": 0,
    "Year": 2025,
    "Offense": "Pocket-picking"
  },
  {
    "YTDCount": 37,
    "Year": 2019,
    "Offense": "Purse-snatching"
  },
  {
    "YTDCount": 58,
    "Year": 2020,
    "Offense": "Purse-snatching",
    "PrevYTDCount": 37,
    "YTDPercentageChange": 56.7568
  },
  {
    "YTDCount": 21,
    "Year": 2021,
    "Offense": "Purse-snatching",
    "PrevYTDCount": 58,
    "YTDPercentageChange": -63.7931
  },
  {
    "YTDCount": 31,
    "Year": 2022,
    "Offense": "Purse-snatching",
    "PrevYTDCount": 21,
    "YTDPercentageChange": 47.619
  },
  {
    "YTDCount": 17,
    "Year": 2023,
    "Offense": "Purse-snatching",
    "PrevYTDCount": 31,
    "YTDPercentageChange": -45.1613
  },
  {
    "YTDCount": 16,
    "Year": 2024,
    "Offense": "Purse-snatching",
    "PrevYTDCount": 17,
    "YTDPercentageChange": -5.8824
  },
  {
    "YTDCount": 9,
    "Year": 2025,
    "Offense": "Purse-snatching",
    "PrevYTDCount": 16,
    "YTDPercentageChange": -43.75
  },
  {
    "YTDCount": 186,
    "Year": 2019,
    "Offense": "Shoplifting"
  },
  {
    "YTDCount": 197,
    "Year": 2020,
    "Offense": "Shoplifting",
    "PrevYTDCount": 186,
    "YTDPercentageChange": 5.914
  },
  {
    "YTDCount": 73,
    "Year": 2021,
    "Offense": "Shoplifting",
    "PrevYTDCount": 197,
    "YTDPercentageChange": -62.9442
  },
  {
    "YTDCount": 54,
    "Year": 2022,
    "Offense": "Shoplifting",
    "PrevYTDCount": 73,
    "YTDPercentageChange": -26.0274
  },
  {
    "YTDCount": 92,
    "Year": 2023,
    "Offense": "Shoplifting",
    "PrevYTDCount": 54,
    "YTDPercentageChange": 70.3704
  },
  {
    "YTDCount": 128,
    "Year": 2024,
    "Offense": "Shoplifting",
    "PrevYTDCount": 92,
    "YTDPercentageChange": 39.1304
  },
  {
    "YTDCount": 164,
    "Year": 2025,
    "Offense": "Shoplifting",
    "PrevYTDCount": 128,
    "YTDPercentageChange": 28.125
  },
  {
    "YTDCount": 50,
    "Year": 2019,
    "Offense": "Theft From Building"
  },
  {
    "YTDCount": 30,
    "Year": 2020,
    "Offense": "Theft From Building",
    "PrevYTDCount": 50,
    "YTDPercentageChange": -40
  },
  {
    "YTDCount": 9,
    "Year": 2021,
    "Offense": "Theft From Building",
    "PrevYTDCount": 30,
    "YTDPercentageChange": -70
  },
  {
    "YTDCount": 30,
    "Year": 2022,
    "Offense": "Theft From Building",
    "PrevYTDCount": 9,
    "YTDPercentageChange": 233.3333
  },
  {
    "YTDCount": 15,
    "Year": 2023,
    "Offense": "Theft From Building",
    "PrevYTDCount": 30,
    "YTDPercentageChange": -50
  },
  {
    "YTDCount": 27,
    "Year": 2024,
    "Offense": "Theft From Building",
    "PrevYTDCount": 15,
    "YTDPercentageChange": 80
  },
  {
    "YTDCount": 31,
    "Year": 2025,
    "Offense": "Theft From Building",
    "PrevYTDCount": 27,
    "YTDPercentageChange": 14.8148
  },
  {
    "YTDCount": 2,
    "Year": 2019,
    "Offense": "Theft From Coin-Operated Machine or Device"
  },
  {
    "YTDCount": 0,
    "Year": 2020,
    "Offense": "Theft From Coin-Operated Machine or Device",
    "PrevYTDCount": 2,
    "YTDPercentageChange": -100
  },
  {
    "YTDCount": 0,
    "Year": 2021,
    "Offense": "Theft From Coin-Operated Machine or Device"
  },
  {
    "YTDCount": 0,
    "Year": 2022,
    "Offense": "Theft From Coin-Operated Machine or Device"
  },
  {
    "YTDCount": 1,
    "Year": 2023,
    "Offense": "Theft From Coin-Operated Machine or Device"
  },
  {
    "YTDCount": 1,
    "Year": 2024,
    "Offense": "Theft From Coin-Operated Machine or Device",
    "PrevYTDCount": 1,
    "YTDPercentageChange": 0
  },
  {
    "YTDCount": 1,
    "Year": 2025,
    "Offense": "Theft From Coin-Operated Machine or Device",
    "PrevYTDCount": 1,
    "YTDPercentageChange": 0
  },
  {
    "YTDCount": 28,
    "Year": 2019,
    "Offense": "Theft of Motor Vehicle Parts or Accessories"
  },
  {
    "YTDCount": 357,
    "Year": 2020,
    "Offense": "Theft of Motor Vehicle Parts or Accessories",
    "PrevYTDCount": 28,
    "YTDPercentageChange": 1175
  },
  {
    "YTDCount": 522,
    "Year": 2021,
    "Offense": "Theft of Motor Vehicle Parts or Accessories",
    "PrevYTDCount": 357,
    "YTDPercentageChange": 46.2185
  },
  {
    "YTDCount": 838,
    "Year": 2022,
    "Offense": "Theft of Motor Vehicle Parts or Accessories",
    "PrevYTDCount": 522,
    "YTDPercentageChange": 60.5364
  },
  {
    "YTDCount": 428,
    "Year": 2023,
    "Offense": "Theft of Motor Vehicle Parts or Accessories",
    "PrevYTDCount": 838,
    "YTDPercentageChange": -48.926
  },
  {
    "YTDCount": 276,
    "Year": 2024,
    "Offense": "Theft of Motor Vehicle Parts or Accessories",
    "PrevYTDCount": 428,
    "YTDPercentageChange": -35.514
  },
  {
    "YTDCount": 203,
    "Year": 2025,
    "Offense": "Theft of Motor Vehicle Parts or Accessories",
    "PrevYTDCount": 276,
    "YTDPercentageChange": -26.4493
  }
]
