[
  {
    "YTDCount": 1635,
    "Year": 2019,
    "Offense": "All Other Larceny"
  },
  {
    "YTDCount": 1574,
    "Year": 2020,
    "Offense": "All Other Larceny",
    "PrevYTDCount": 1635,
    "YTDPercentageChange": -3.7309
  },
  {
    "YTDCount": 1203,
    "Year": 2021,
    "Offense": "All Other Larceny",
    "PrevYTDCount": 1574,
    "YTDPercentageChange": -23.5705
  },
  {
    "YTDCount": 1511,
    "Year": 2022,
    "Offense": "All Other Larceny",
    "PrevYTDCount": 1203,
    "YTDPercentageChange": 25.6027
  },
  {
    "YTDCount": 1337,
    "Year": 2023,
    "Offense": "All Other Larceny",
    "PrevYTDCount": 1511,
    "YTDPercentageChange": -11.5156
  },
  {
    "YTDCount": 1609,
    "Year": 2024,
    "Offense": "All Other Larceny",
    "PrevYTDCount": 1337,
    "YTDPercentageChange": 20.3441
  },
  {
    "YTDCount": 1030,
    "Year": 2019,
    "Offense": "Theft From Motor Vehicle"
  },
  {
    "YTDCount": 1127,
    "Year": 2020,
    "Offense": "Theft From Motor Vehicle",
    "PrevYTDCount": 1030,
    "YTDPercentageChange": 9.4175
  },
  {
    "YTDCount": 766,
    "Year": 2021,
    "Offense": "Theft From Motor Vehicle",
    "PrevYTDCount": 1127,
    "YTDPercentageChange": -32.0319
  },
  {
    "YTDCount": 869,
    "Year": 2022,
    "Offense": "Theft From Motor Vehicle",
    "PrevYTDCount": 766,
    "YTDPercentageChange": 13.4465
  },
  {
    "YTDCount": 1004,
    "Year": 2023,
    "Offense": "Theft From Motor Vehicle",
    "PrevYTDCount": 869,
    "YTDPercentageChange": 15.5351
  },
  {
    "YTDCount": 896,
    "Year": 2024,
    "Offense": "Theft From Motor Vehicle",
    "PrevYTDCount": 1004,
    "YTDPercentageChange": -10.757
  },
  {
    "YTDCount": 5,
    "Year": 2019,
    "Offense": "Pocket-picking"
  },
  {
    "YTDCount": 4,
    "Year": 2020,
    "Offense": "Pocket-picking",
    "PrevYTDCount": 5,
    "YTDPercentageChange": -20
  },
  {
    "YTDCount": 0,
    "Year": 2021,
    "Offense": "Pocket-picking",
    "PrevYTDCount": 4,
    "YTDPercentageChange": -100
  },
  {
    "YTDCount": 0,
    "Year": 2022,
    "Offense": "Pocket-picking"
  },
  {
    "YTDCount": 0,
    "Year": 2023,
    "Offense": "Pocket-picking"
  },
  {
    "YTDCount": 1,
    "Year": 2024,
    "Offense": "Pocket-picking"
  },
  {
    "YTDCount": 65,
    "Year": 2019,
    "Offense": "Purse-snatching"
  },
  {
    "YTDCount": 85,
    "Year": 2020,
    "Offense": "Purse-snatching",
    "PrevYTDCount": 65,
    "YTDPercentageChange": 30.7692
  },
  {
    "YTDCount": 41,
    "Year": 2021,
    "Offense": "Purse-snatching",
    "PrevYTDCount": 85,
    "YTDPercentageChange": -51.7647
  },
  {
    "YTDCount": 45,
    "Year": 2022,
    "Offense": "Purse-snatching",
    "PrevYTDCount": 41,
    "YTDPercentageChange": 9.7561
  },
  {
    "YTDCount": 27,
    "Year": 2023,
    "Offense": "Purse-snatching",
    "PrevYTDCount": 45,
    "YTDPercentageChange": -40
  },
  {
    "YTDCount": 27,
    "Year": 2024,
    "Offense": "Purse-snatching",
    "PrevYTDCount": 27,
    "YTDPercentageChange": 0
  },
  {
    "YTDCount": 322,
    "Year": 2019,
    "Offense": "Shoplifting"
  },
  {
    "YTDCount": 287,
    "Year": 2020,
    "Offense": "Shoplifting",
    "PrevYTDCount": 322,
    "YTDPercentageChange": -10.8696
  },
  {
    "YTDCount": 100,
    "Year": 2021,
    "Offense": "Shoplifting",
    "PrevYTDCount": 287,
    "YTDPercentageChange": -65.1568
  },
  {
    "YTDCount": 130,
    "Year": 2022,
    "Offense": "Shoplifting",
    "PrevYTDCount": 100,
    "YTDPercentageChange": 30
  },
  {
    "YTDCount": 151,
    "Year": 2023,
    "Offense": "Shoplifting",
    "PrevYTDCount": 130,
    "YTDPercentageChange": 16.1538
  },
  {
    "YTDCount": 198,
    "Year": 2024,
    "Offense": "Shoplifting",
    "PrevYTDCount": 151,
    "YTDPercentageChange": 31.1258
  },
  {
    "YTDCount": 74,
    "Year": 2019,
    "Offense": "Theft From Building"
  },
  {
    "YTDCount": 47,
    "Year": 2020,
    "Offense": "Theft From Building",
    "PrevYTDCount": 74,
    "YTDPercentageChange": -36.4865
  },
  {
    "YTDCount": 15,
    "Year": 2021,
    "Offense": "Theft From Building",
    "PrevYTDCount": 47,
    "YTDPercentageChange": -68.0851
  },
  {
    "YTDCount": 43,
    "Year": 2022,
    "Offense": "Theft From Building",
    "PrevYTDCount": 15,
    "YTDPercentageChange": 186.6667
  },
  {
    "YTDCount": 25,
    "Year": 2023,
    "Offense": "Theft From Building",
    "PrevYTDCount": 43,
    "YTDPercentageChange": -41.8605
  },
  {
    "YTDCount": 39,
    "Year": 2024,
    "Offense": "Theft From Building",
    "PrevYTDCount": 25,
    "YTDPercentageChange": 56
  },
  {
    "YTDCount": 2,
    "Year": 2019,
    "Offense": "Theft From Coin-Operated Machine or Device"
  },
  {
    "YTDCount": 0,
    "Year": 2020,
    "Offense": "Theft From Coin-Operated Machine or Device",
    "PrevYTDCount": 2,
    "YTDPercentageChange": -100
  },
  {
    "YTDCount": 0,
    "Year": 2021,
    "Offense": "Theft From Coin-Operated Machine or Device"
  },
  {
    "YTDCount": 0,
    "Year": 2022,
    "Offense": "Theft From Coin-Operated Machine or Device"
  },
  {
    "YTDCount": 1,
    "Year": 2023,
    "Offense": "Theft From Coin-Operated Machine or Device"
  },
  {
    "YTDCount": 1,
    "Year": 2024,
    "Offense": "Theft From Coin-Operated Machine or Device",
    "PrevYTDCount": 1,
    "YTDPercentageChange": 0
  },
  {
    "YTDCount": 61,
    "Year": 2019,
    "Offense": "Theft of Motor Vehicle Parts or Accessories"
  },
  {
    "YTDCount": 547,
    "Year": 2020,
    "Offense": "Theft of Motor Vehicle Parts or Accessories",
    "PrevYTDCount": 61,
    "YTDPercentageChange": 796.7213
  },
  {
    "YTDCount": 740,
    "Year": 2021,
    "Offense": "Theft of Motor Vehicle Parts or Accessories",
    "PrevYTDCount": 547,
    "YTDPercentageChange": 35.2834
  },
  {
    "YTDCount": 1327,
    "Year": 2022,
    "Offense": "Theft of Motor Vehicle Parts or Accessories",
    "PrevYTDCount": 740,
    "YTDPercentageChange": 79.3243
  },
  {
    "YTDCount": 643,
    "Year": 2023,
    "Offense": "Theft of Motor Vehicle Parts or Accessories",
    "PrevYTDCount": 1327,
    "YTDPercentageChange": -51.5448
  },
  {
    "YTDCount": 367,
    "Year": 2024,
    "Offense": "Theft of Motor Vehicle Parts or Accessories",
    "PrevYTDCount": 643,
    "YTDPercentageChange": -42.9238
  }
]
