[
  {
    "YTDCount": 382,
    "Year": 2019,
    "Offense": "Sex Offenses"
  },
  {
    "YTDCount": 291,
    "Year": 2020,
    "Offense": "Sex Offenses",
    "PrevYTDCount": 382,
    "YTDPercentageChange": -23.822
  },
  {
    "YTDCount": 289,
    "Year": 2021,
    "Offense": "Sex Offenses",
    "PrevYTDCount": 291,
    "YTDPercentageChange": -0.6873
  },
  {
    "YTDCount": 273,
    "Year": 2022,
    "Offense": "Sex Offenses",
    "PrevYTDCount": 289,
    "YTDPercentageChange": -5.5363
  },
  {
    "YTDCount": 316,
    "Year": 2023,
    "Offense": "Sex Offenses",
    "PrevYTDCount": 273,
    "YTDPercentageChange": 15.7509
  },
  {
    "YTDCount": 316,
    "Year": 2024,
    "Offense": "Sex Offenses",
    "PrevYTDCount": 316,
    "YTDPercentageChange": 0
  }
]
