[
  {
    "YTDCount": 108,
    "Year": 2019,
    "Offense": "Robbery"
  },
  {
    "YTDCount": 160,
    "Year": 2020,
    "Offense": "Robbery",
    "PrevYTDCount": 108,
    "YTDPercentageChange": 48.1481
  },
  {
    "YTDCount": 250,
    "Year": 2021,
    "Offense": "Robbery",
    "PrevYTDCount": 160,
    "YTDPercentageChange": 56.25
  },
  {
    "YTDCount": 242,
    "Year": 2022,
    "Offense": "Robbery",
    "PrevYTDCount": 250,
    "YTDPercentageChange": -3.2
  },
  {
    "YTDCount": 162,
    "Year": 2023,
    "Offense": "Robbery",
    "PrevYTDCount": 242,
    "YTDPercentageChange": -33.0579
  },
  {
    "YTDCount": 227,
    "Year": 2024,
    "Offense": "Robbery",
    "PrevYTDCount": 162,
    "YTDPercentageChange": 40.1235
  },
  {
    "YTDCount": 126,
    "Year": 2025,
    "Offense": "Robbery",
    "PrevYTDCount": 227,
    "YTDPercentageChange": -44.4934
  }
]
