[
  {
    "YTDCount": 872,
    "Year": 2019,
    "Offense": "Robbery"
  },
  {
    "YTDCount": 1127,
    "Year": 2020,
    "Offense": "Robbery",
    "PrevYTDCount": 872,
    "YTDPercentageChange": 29.2431
  },
  {
    "YTDCount": 1214,
    "Year": 2021,
    "Offense": "Robbery",
    "PrevYTDCount": 1127,
    "YTDPercentageChange": 7.7196
  },
  {
    "YTDCount": 1262,
    "Year": 2022,
    "Offense": "Robbery",
    "PrevYTDCount": 1214,
    "YTDPercentageChange": 3.9539
  },
  {
    "YTDCount": 941,
    "Year": 2023,
    "Offense": "Robbery",
    "PrevYTDCount": 1262,
    "YTDPercentageChange": -25.4358
  },
  {
    "YTDCount": 1120,
    "Year": 2024,
    "Offense": "Robbery",
    "PrevYTDCount": 941,
    "YTDPercentageChange": 19.0223
  },
  {
    "YTDCount": 719,
    "Year": 2025,
    "Offense": "Robbery",
    "PrevYTDCount": 1120,
    "YTDPercentageChange": -35.8036
  }
]
